{
  "notes": [
    {
      "id": 1,
      "content": "custom hooks are awesome"
    },
    {
      "id": 2,
      "content": "best feature ever <3"
    },
    {
      "content": "test",
      "id": 3
    },
    {
      "content": "test",
      "id": 4
    },
    {
      "content": "testicito",
      "id": 5
    },
    {
      "content": "otro mas",
      "id": 6
    },
    {
      "content": "otro mas",
      "id": 7
    },
    {
      "content": "",
      "id": 8
    },
    {
      "content": "crear",
      "id": 9
    },
    {
      "content": "crear",
      "id": 10
    },
    {
      "content": "crear",
      "id": 11
    },
    {
      "content": "creartest",
      "id": 12
    },
    {
      "content": "creartest",
      "id": 13
    },
    {
      "content": "creartest",
      "id": 14
    },
    {
      "content": "creartest",
      "id": 15
    }
  ],
  "persons": [
    {
      "id": 1,
      "name": "Matti Luukkainen",
      "number": "040-12344565"
    },
    {
      "id": 2,
      "name": "Tarja Halonen",
      "number": "040-2223334"
    },
    {
      "name": "asdasd",
      "number": "32452345",
      "id": 3
    },
    {
      "name": "asdasd",
      "number": "32452345",
      "id": 4
    },
    {
      "name": "asdasd",
      "number": "32452345",
      "id": 5
    },
    {
      "name": "asdasd",
      "number": "32452345",
      "id": 6
    },
    {
      "name": "asdasd",
      "number": "32452345",
      "id": 7
    },
    {
      "name": "test",
      "number": "dsdsada",
      "id": 8
    },
    {
      "name": "test",
      "number": "dsdsada",
      "id": 9
    }
  ]
}